xrsmtp/__init__.py
xrsmtp-1.0.4.dist-info/METADATA
xrsmtp-1.0.4.dist-info/WHEEL
xrsmtp-1.0.4.dist-info/top_level.txt
xrsmtp-1.0.4.dist-info/RECORD
