Metadata-Version: 2.1
Name: xrsmtp
Version: 1.0.4
Summary: XploitsR | XRSmtp is a module for fetching the details of any SMTP provider for your development or personal use.
Home-page: https://github.com/XploitsR/XRSmtp
Author: XploitsR Author (solomon narh)
Author-email: solomonnarh97062@gmail.com
License: MIT
Platform: UNKNOWN
Classifier: Programming Language :: Python :: 3
Classifier: License :: OSI Approved :: MIT License
Classifier: Operating System :: OS Independent
